ALU/alu.sv
module alu(input logic [7:0] a, 
            input logic [7:0] b,
            input logic [1:0] ALUControl,
            output logic [7:0] ALUResult);

always_comb
    case(ALUControl)
    2'b00 : ALUResult = a & b; //and
    2'b01 : ALUResult = a | b; //or
    2'b10 : ALUResult = a + b;  //add
    2'b11 : ALUResult = a - b;  //subtract
    default : ALUResult = 8'bx;
    endcase

endmodule

reg/reg_file.sv
module reg_file(input logic [3:0] RA1, RA2, WA,
                input logic [7:0] data_in,
                input logic clk, reset, write_enable,
                output logic [7:0] data_out1, data_out2);

logic [7:0] rf [0:15];

assign data_out1 = rf[RA1];
assign data_out2 = rf[RA2];

always_ff @ (posedge clk)
    if (write_enable)
    rf[WA] <= data_in;
endmodule

reg_file_alu/reg_file_alu.sv
`include "reg_file.sv"//including the files used for reg and alu
`include "alu.sv"

module reg_file_alu(input logic [3:0] RA1, RA2, WA,
        input logic [7:0] external_data_in,
        input logic clk, reset, RegWrite, ALUSrc,
        input logic [1:0] ALUControl,
        output logic [7:0] ALUResult);

logic [7:0] RD1, RD2, SrcA, SrcB;

reg_file reg_file(.RA1(RA1), .RA2(RA2), .WA(WA), .data_in(ALUResult),
                .clk(clk), .reset(reset), .write_enable(RegWrite),
                .data_out1(RD1), .data_out2(RD2));
                
alu alu(.a(SrcA), .b(SrcB), .ALUControl(ALUControl), 
        .ALUResult(ALUResult));

assign SrcA = RD1;

always_comb
    case(ALUSrc)
    1'b0:
        SrcB = RD2;
    1'b1:
        SrcB = external_data_in;
    default:
        SrcB = 8'bx;
    endcase

endmodule

reg_file_alu/reg_file_alu_tb.sv
`timescale 1ps/1ps
`include "reg_file_alu.sv"

module reg_file_alu_tb;
logic [3:0] RA1, RA2, WA;
logic [7:0] external_data_in;
logic clk, reset, RegWrite, ALUSrc;
logic [1:0] ALUControl;
logic [7:0] ALUResult;

reg_file_alu dut (RA1, RA2, WA, external_data_in, clk, reset, RegWrite, ALUSrc, ALUControl, ALUResult);

initial begin 
    clk = 0;
    forever #10 clk = ~clk;
end

initial begin
    $dumpfile("reg_file_alu_tb.vcd");
    $dumpvars(0, reg_file_alu_tb);
    reset = 1;
    #10 reset = 0;

    #10 RegWrite = 1;

    #10 external_data_in = 0; ALUSrc = 1; ALUControl =  2'b00; WA = 1; //use reg 1 to add external
    #10 external_data_in = 1; ALUSrc = 1; ALUControl =  2'b01; WA = 2; //data of 1 should be stored in reg 2

    #10 external_data_in = 4; ALUSrc = 1; ALUControl =  2'b01; WA = 4; //use reg 1 to add external
    #10 external_data_in = 5; ALUSrc = 1; ALUControl =  2'b01; WA = 5; //data of 1 should be stored in reg 2

    #10 RegWrite = 0; RA1 = 5; RA2 = 4; ALUSrc = 0; ALUControl = 2'b11; 
    $finish;
end

initial begin // Response monitor
    $monitor ("t = %3d | clk = %b | reset = %b | RA1 = %b | RA2 = %b | \
            WA = %b | RegWrite = %b | external_data_in = %b | ALUResult = %b | \
            ALUSrc = %b | ALUControl = %b | ", $time, clk, reset, RA1, RA2, WA,
            RegWrite, external_data_in, ALUResult, ALUSrc, ALUControl);
end

endmodule

reg_file_alu/reg_file_alu_tb.vcd
$date
	Wed Mar 09 14:38:13 2022
$end
$version
	Icarus Verilog
$end
$timescale
	1ps
$end
$scope module reg_file_alu_tb $end
$var wire 8 ! ALUResult [7:0] $end
$var reg 2 " ALUControl [1:0] $end
$var reg 1 # ALUSrc $end
$var reg 4 $ RA1 [3:0] $end
$var reg 4 % RA2 [3:0] $end
$var reg 1 & RegWrite $end
$var reg 4 ' WA [3:0] $end
$var reg 1 ( clk $end
$var reg 8 ) external_data_in [7:0] $end
$var reg 1 * reset $end
$scope module dut $end
$var wire 2 + ALUControl [1:0] $end
$var wire 1 # ALUSrc $end
$var wire 4 , RA1 [3:0] $end
$var wire 4 - RA2 [3:0] $end
$var wire 1 & RegWrite $end
$var wire 8 . SrcA [7:0] $end
$var wire 4 / WA [3:0] $end
$var wire 1 ( clk $end
$var wire 8 0 external_data_in [7:0] $end
$var wire 1 * reset $end
$var wire 8 1 RD2 [7:0] $end
$var wire 8 2 RD1 [7:0] $end
$var wire 8 3 ALUResult [7:0] $end
$var reg 8 4 SrcB [7:0] $end
$scope module alu $end
$var wire 2 5 ALUControl [1:0] $end
$var wire 8 6 a [7:0] $end
$var wire 8 7 b [7:0] $end
$var reg 8 8 ALUResult [7:0] $end
$upscope $end
$scope module reg_file $end
$var wire 4 9 RA1 [3:0] $end
$var wire 4 : RA2 [3:0] $end
$var wire 4 ; WA [3:0] $end
$var wire 1 ( clk $end
$var wire 8 < data_in [7:0] $end
$var wire 8 = data_out1 [7:0] $end
$var wire 8 > data_out2 [7:0] $end
$var wire 1 * reset $end
$var wire 1 & write_enable $end
$upscope $end
$upscope $end
$upscope $end
$enddefinitions $end
#0
$dumpvars
bx >
bx =
bx <
bx ;
bx :
bx 9
bx 8
bx 7
bx 6
bx 5
bx 4
bx 3
bx 2
bx 1
bx 0
bx /
bx .
bx -
bx ,
bx +
1*
bx )
0(
bx '
x&
bx %
bx $
x#
bx "
bx !
$end
#10
0*
1(
#20
1&
0(
#30
b0 !
b0 3
b0 8
b0 <
b0 4
b0 7
b1 '
b1 /
b1 ;
b0 "
b0 +
b0 5
1#
b0 )
b0 0
1(
#40
bx1 !
bx1 3
bx1 8
bx1 <
b1 4
b1 7
b10 '
b10 /
b10 ;
b1 "
b1 +
b1 5
b1 )
b1 0
0(
#50
bx1xx !
bx1xx 3
bx1xx 8
bx1xx <
b100 4
b100 7
b100 '
b100 /
b100 ;
b100 )
b100 0
1(
#60
bx1x1 !
bx1x1 3
bx1x1 8
bx1x1 <
b101 4
b101 7
b101 '
b101 /
b101 ;
b101 )
b101 0
0(
#70
bx !
bx 3
bx 8
bx <
bx1 4
bx1 7
b11 "
b11 +
b11 5
0#
bx1 1
bx1 >
b100 %
b100 -
b100 :
b101 $
b101 ,
b101 9
0&
1(
