reg/reg_file.sv
module reg_file(input logic [3:0] RA1, RA2, WA,
                input logic [7:0] data_in,
                input logic clk, reset, write_enable,
                output logic [7:0] data_out1, data_out2);

logic [7:0] rf [0:15];

assign data_out1 = rf[RA1];
assign data_out2 = rf[RA2];

always_ff @ (posedge clk)
    if (write_enable)
    rf[WA] <= data_in;
endmodule

reg/reg_file_tb.sv
`timescale 1ps/1ps
`include "reg_file.sv"

module reg_file_tb;
logic [3:0] RA1, RA2, WA;
logic clk, reset, write_enable;
logic [7:0] data_in, data_out1, data_out2;

reg_file dut (RA1, RA2, WA, data_in, clk, reset, write_enable, data_out1, data_out2);

initial begin 
    clk = 0;
    forever #10 clk = ~clk;
end

initial begin
    $dumpfile("reg_file_tb.vcd");
    $dumpvars(0, reg_file_tb);
    RA1 = 1; RA2 = 2; WA = 0; data_in = 5; write_enable = 0;
    reset = 1;
    #10 reset = 0;
    #15 write_enable = 1; //open to write
    #20 WA = 1; data_in = 2;
    #20 WA = 3; data_in = 4;
    #20 WA = 5; data_in = 6;
    #20 WA = 7; data_in = 8;
    #20 WA = 9; data_in = 10;
    #20 WA = 11; data_in = 12;
    #20 WA = 13; data_in = 14;
    #20 WA = 15; data_in = 16;
    #20 write_enable = 0;
    #20 RA1 = 1; RA2 = 3;
    #20 RA1 = 5; RA2 = 7;
    #20 RA1 = 9; RA2 = 11;
    #20 RA1 = 13; RA2 = 15;
    #30;
    $finish;
end

initial begin // Response monitor
    $monitor ("t = %3d | clk = %b | reset = %b | RA1 = %b | RA2 = %b | \
            WA = %b | write_enable = %b | data_in = %b | data_out1 = %b | \
            data_out2 = %b", $time, clk, reset, RA1, RA2, WA, write_enable, data_in, data_out1, data_out2);
end

endmodule

reg/reg_file_tb.vcd
$date
	Tue Mar 08 16:15:52 2022
$end
$version
	Icarus Verilog
$end
$timescale
	1ps
$end
$scope module reg_file_tb $end
$var wire 8 ! data_out2 [7:0] $end
$var wire 8 " data_out1 [7:0] $end
$var reg 4 # RA1 [3:0] $end
$var reg 4 $ RA2 [3:0] $end
$var reg 4 % WA [3:0] $end
$var reg 1 & clk $end
$var reg 8 ' data_in [7:0] $end
$var reg 1 ( reset $end
$var reg 1 ) write_enable $end
$scope module dut $end
$var wire 4 * RA1 [3:0] $end
$var wire 4 + RA2 [3:0] $end
$var wire 4 , WA [3:0] $end
$var wire 1 & clk $end
$var wire 8 - data_in [7:0] $end
$var wire 8 . data_out1 [7:0] $end
$var wire 8 / data_out2 [7:0] $end
$var wire 1 ( reset $end
$var wire 1 ) write_enable $end
$upscope $end
$upscope $end
$enddefinitions $end
#0
$dumpvars
bx /
bx .
b101 -
b0 ,
b10 +
b1 *
0)
1(
b101 '
0&
b0 %
b10 $
b1 #
bx "
bx !
$end
#10
0(
1&
#20
0&
#25
1)
#30
1&
#40
0&
#45
b10 '
b10 -
b1 %
b1 ,
#50
b10 "
b10 .
1&
#60
0&
#65
b100 '
b100 -
b11 %
b11 ,
#70
1&
#80
0&
#85
b110 '
b110 -
b101 %
b101 ,
#90
1&
#100
0&
#105
b1000 '
b1000 -
b111 %
b111 ,
#110
1&
#120
0&
#125
b1010 '
b1010 -
b1001 %
b1001 ,
#130
1&
#140
0&
#145
b1100 '
b1100 -
b1011 %
b1011 ,
#150
1&
#160
0&
#165
b1110 '
b1110 -
b1101 %
b1101 ,
#170
1&
#180
0&
#185
b10000 '
b10000 -
b1111 %
b1111 ,
#190
1&
#200
0&
#205
0)
#210
1&
#220
0&
#225
b100 !
b100 /
b11 $
b11 +
#230
1&
#240
0&
#245
b1000 !
b1000 /
b111 $
b111 +
b110 "
b110 .
b101 #
b101 *
#250
1&
#260
0&
#265
b1100 !
b1100 /
b1011 $
b1011 +
b1010 "
b1010 .
b1001 #
b1001 *
#270
1&
#280
0&
#285
b10000 !
b10000 /
b1111 $
b1111 +
b1110 "
b1110 .
b1101 #
b1101 *
